[
  {
    "element": "Link",
    "props": {
      "children": "Modes",
      "href": "/modes/"
    }
  },
  {
    "element": "Link",
    "props": {
      "children": "Configuration",
      "href": "/configuration/"
    }
  },
  {
    "element": "Link",
    "props": {
      "children": "Routing",
      "href": "/routing/"
    }
  },
  {
    "element": "Link",
    "props": {
      "children": "Concepts",
      "href": "/concepts/"
    }
  },
  {
    "element": "Link",
    "props": {
      "children": "Deployment",
      "href": "/deployment/"
    }
  },
  {
    "element": "Link",
    "props": {
      "children": "Playground",
      "href": "/playground/"
    }
  }
]
